{
  "name": "dbTechLayerCutClassRule",
  "type": "dbObject",
  "fields": [
    {
      "name": "_name",
      "type": "char *",
      "flags": [
        "no-set"
      ]
    },
    {
      "type": "int",
      "name": "width_"
    },
    {
      "type": "int",
      "name": "length_"
    },
    {
      "type": "int",
      "name": "num_cuts_"
    },
    {
      "type": "bit",
      "name": "length_valid_"
    },
    {
      "type": "bit",
      "name": "cuts_valid_"
    }
  ],
  "cpp_includes": [
    "dbTechLayer.h",
    "dbHashTable.h"
  ]
}